mcap2timescale/__init__.py
mcap2timescale/job.py
mcap2timescale/main.py
mcap2timescale/rosbag.py
mcap2timescale/timescale.py
mcap2timescale-0.1.2.dist-info/METADATA
mcap2timescale-0.1.2.dist-info/WHEEL
mcap2timescale-0.1.2.dist-info/entry_points.txt
mcap2timescale-0.1.2.dist-info/top_level.txt
mcap2timescale-0.1.2.dist-info/RECORD
